slacklog/__init__.py
slacklog/formatters.py
slacklog/models.py
slacklog/parsers.py
slacklog/scripts.py
slacklog-0.9.6.dist-info/LICENSE.txt
slacklog-0.9.6.dist-info/METADATA
slacklog-0.9.6.dist-info/WHEEL
slacklog-0.9.6.dist-info/entry_points.txt
slacklog-0.9.6.dist-info/top_level.txt
slacklog-0.9.6.dist-info/RECORD
