Metadata-Version: 2.1
Name: slacklog
Version: 0.9.6
Summary: Convert Slackware ChangeLog to various formats
Home-page: http://pypi.python.org/pypi/slacklog/
Author: Mikko Värri
Author-email: vmj@linuxbox.fi
Maintainer: Mikko Värri
Maintainer-email: vmj@linuxbox.fi
License: UNKNOWN
Project-URL: Documentation, https://slacklog.readthedocs.org
Project-URL: Source, https://github.com/vmj/slacklog
Project-URL: Build status, https://travis-ci.org/vmj/slacklog
Keywords: slackware changelog rss atom
Platform: UNKNOWN
Classifier: Development Status :: 4 - Beta
Classifier: Environment :: Console
Classifier: Intended Audience :: Developers
Classifier: Intended Audience :: System Administrators
Classifier: License :: OSI Approved :: GNU General Public License v3 or later (GPLv3+)
Classifier: Operating System :: OS Independent
Classifier: Programming Language :: Python
Classifier: Programming Language :: Python :: 2.7
Classifier: Programming Language :: Python :: 3.4
Classifier: Programming Language :: Python :: 3.5
Classifier: Programming Language :: Python :: 3.6
Classifier: Programming Language :: Python :: 3.7
Classifier: Topic :: Internet :: WWW/HTTP :: Dynamic Content :: News/Diary
Classifier: Topic :: Utilities
Requires-Python: >=2.7, !=3.0.*, !=3.1.*, !=3.2.*, !=3.3.*, <4
Requires-Dist: python-dateutil (<3,>=2.1)
